wbwriter/__init__.py
wbwriter/admin.py
wbwriter/apps.py
wbwriter/dynamic_preferences_registry.py
wbwriter/pdf_generator.py
wbwriter/publication_parser.py
wbwriter/typings.py
wbwriter/urls.py
wbwriter/factories/__init__.py
wbwriter/factories/article.py
wbwriter/factories/meta_information.py
wbwriter/filters/__init__.py
wbwriter/filters/article.py
wbwriter/filters/metainformationinstance.py
wbwriter/migrations/0001_initial_squashed_squashed_0008_alter_article_author_alter_article_feedback_contact_and_more.py
wbwriter/migrations/0009_dependantarticle.py
wbwriter/migrations/0010_alter_article_options.py
wbwriter/migrations/0011_auto_20240103_0953.py
wbwriter/migrations/__init__.py
wbwriter/models/__init__.py
wbwriter/models/article.py
wbwriter/models/article_type.py
wbwriter/models/block.py
wbwriter/models/block_parameter.py
wbwriter/models/in_editor_template.py
wbwriter/models/meta_information.py
wbwriter/models/mixins.py
wbwriter/models/publication_models.py
wbwriter/models/style.py
wbwriter/models/template.py
wbwriter/serializers/__init__.py
wbwriter/serializers/article.py
wbwriter/serializers/article_type.py
wbwriter/serializers/in_editor_template.py
wbwriter/serializers/meta_information.py
wbwriter/serializers/publication.py
wbwriter/templates/wbwriter/article_pdf.html
wbwriter/templates/wbwriter/templatetags/cite_article.html
wbwriter/templates/wbwriter/templatetags/table_of_contents.html
wbwriter/templates/wbwriter/templatetags/table_of_contents_articles.html
wbwriter/templatetags/__init__.py
wbwriter/templatetags/writer.py
wbwriter/tests/__init__.py
wbwriter/tests/conftest.py
wbwriter/tests/signals.py
wbwriter/tests/test_filter.py
wbwriter/tests/test_model.py
wbwriter/tests/test_writer.py
wbwriter/tests/tests.py
wbwriter/viewsets/__init__.py
wbwriter/viewsets/article.py
wbwriter/viewsets/article_type.py
wbwriter/viewsets/buttons.py
wbwriter/viewsets/in_editor_template.py
wbwriter/viewsets/menu.py
wbwriter/viewsets/meta_information.py
wbwriter-2.2.6.dist-info/METADATA
wbwriter-2.2.6.dist-info/WHEEL
wbwriter-2.2.6.dist-info/RECORD
