Metadata-Version: 2.4
Name: wbwriter
Version: 2.2.6
Author-email: Christopher Wittlinger <c.wittlinger@stainly.com>
Requires-Dist: pillow==9.1.*
Requires-Dist: reportlab==3.*
Requires-Dist: wbcore
Requires-Dist: weasyprint==57.*
